main.py
uv_test_zx-0.1.0.dist-info/METADATA
uv_test_zx-0.1.0.dist-info/WHEEL
uv_test_zx-0.1.0.dist-info/entry_points.txt
uv_test_zx-0.1.0.dist-info/top_level.txt
uv_test_zx-0.1.0.dist-info/RECORD
