Metadata-Version: 2.4
Name: uv-test-zx
Version: 0.1.0
Summary: Add your description here
Requires-Python: >=3.12
Requires-Dist: mcp>=1.14.0
